{
  "accuracy": 0.6862745098039216,
  "precision": 0.6434676434676434,
  "recall": 0.6665092111478508,
  "f1": 0.6470588235294117,
  "confusion_matrix": [
    [
      52,
      21
    ],
    [
      11,
      18
    ]
  ],
  "num_samples": 102,
  "num_generation_errors": 0,
  "run_info": {
    "model_type": "gemma",
    "model_hf_id": "google/gemma-7b-it",
    "dataset_name": "politifact",
    "k_shot": 8,
    "internal_seed": 42,
    "max_new_tokens": 10,
    "batch_size": 4,
    "max_example_length": 500,
    "effective_device_type": "cuda",
    "execution_time_seconds": 224.2499885559082
  }
}