{
  "k_shot": 13,
  "seed": 42,
  "sampled_unlabeled": true,
  "embedding_type": "roberta",
  "news_news_edge_policy": "knn",
  "labeled_indices_original": [
    47,
    8,
    290,
    127,
    239,
    287,
    308,
    155,
    12,
    363,
    358,
    334,
    368,
    263,
    194,
    280,
    57,
    133,
    183,
    39,
    294,
    347,
    359,
    136,
    125,
    80
  ],
  "labeled_label_distribution": {
    "0": 13,
    "1": 13
  },
  "unlabeled_sample_factor": 10,
  "unlabeled_indices_original_sampled": [
    326,
    344,
    360,
    373,
    102,
    253,
    341,
    29,
    53,
    147,
    201,
    209,
    260,
    281,
    158,
    203,
    251,
    272,
    365,
    49,
    325,
    298,
    36,
    208,
    123,
    197,
    285,
    68,
    216,
    109,
    181,
    152,
    16,
    261,
    255,
    220,
    307,
    316,
    315,
    19,
    286,
    27,
    6,
    219,
    150,
    132,
    313,
    302,
    168,
    314,
    160,
    222,
    282,
    296,
    268,
    324,
    370,
    111,
    22,
    148,
    78,
    291,
    151,
    349,
    45,
    91,
    339,
    245,
    337,
    65,
    246,
    189,
    175,
    104,
    223,
    40,
    345,
    191,
    236,
    38,
    13,
    107,
    234,
    235,
    60,
    134,
    110,
    262,
    348,
    94,
    56,
    200,
    180,
    188,
    50,
    24,
    89,
    275,
    14,
    327,
    157,
    144,
    85,
    174,
    33,
    241,
    207,
    329,
    83,
    51,
    81,
    352,
    243,
    118,
    128,
    25,
    362,
    225,
    169,
    26,
    266,
    121,
    274,
    369,
    162,
    279,
    182,
    137,
    116,
    338,
    63,
    330,
    297,
    10,
    62,
    173,
    138,
    247,
    238,
    9,
    264,
    74,
    252,
    214,
    88,
    237,
    79,
    153,
    131,
    277,
    366,
    46,
    103,
    90,
    335,
    101,
    323,
    140,
    54,
    319,
    100,
    84,
    254,
    322,
    273,
    270,
    178,
    320,
    186,
    86,
    72,
    30,
    271,
    106,
    331,
    377,
    161,
    218,
    58,
    112,
    283,
    119,
    113,
    48,
    258,
    135,
    177,
    380,
    176,
    1,
    213,
    130,
    76,
    146,
    379,
    192,
    333,
    229,
    122,
    328,
    372,
    303,
    256,
    67,
    75,
    156,
    120,
    99,
    249,
    108,
    23,
    356,
    364,
    70,
    61,
    340,
    309,
    69,
    293,
    187,
    105,
    164,
    141,
    34,
    31,
    231,
    87,
    32,
    167,
    299,
    154,
    233,
    242,
    367,
    43,
    212,
    355,
    269,
    7,
    172,
    55,
    93,
    304,
    376,
    226,
    170,
    353,
    142,
    92,
    179,
    375,
    114,
    195,
    221,
    257,
    374,
    354,
    42,
    149,
    244
  ]
}