{
  "nodes": 3024,
  "edges": 48384,
  "avg_degree": 16.0,
  "nodes_train_labeled": 32,
  "nodes_train_unlabeled": 320,
  "nodes_test": 2672,
  "sampling_info": {
    "sampled_unlabeled": true,
    "unlabeled_sample_factor": 10,
    "num_labeled_original": 32,
    "num_unlabeled_sampled_original": 320
  },
  "isolated_nodes": 0,
  "degree_stats": {
    "min": 8,
    "max": 113,
    "mean": 13.567460317460318,
    "median": 10.0,
    "std": 9.23714318309147
  },
  "connected_components": 1,
  "largest_component_size": 3024,
  "avg_path_length": 3.980864955972465,
  "density": 0.004488078173159218,
  "avg_clustering": 0.27127866918285615,
  "assortativity": -0.08049739318298081,
  "edge_types": {
    "train_labeled-train_labeled": 8,
    "train_labeled-train_unlabeled": 124,
    "train_labeled-test": 1056,
    "train_unlabeled-train_unlabeled": 438,
    "train_unlabeled-test": 8812,
    "test-test": 37946,
    "other": 0
  },
  "class_connectivity": {
    "ff": 1540,
    "rr": 14085,
    "fr": 4889
  },
  "homophily_ratio": 0.7616749536901628,
  "test_node_connectivity": {
    "test_nodes_total": 2672,
    "test_nodes_isolated": 0,
    "test_nodes_only_to_test": 687,
    "test_nodes_to_train": 1985
  },
  "power_law": {
    "exponent": 2.804495472615951,
    "r_squared": 0.9228858962687356,
    "p_value": 2.525303658540765e-37,
    "std_err": 0.10133457709771314,
    "is_power_law": "True"
  }
}